{
  "_generated_at_utc": "2026-06-03T09:20:09Z",
  "_total_rows": 150450,
  "_matched_rows": 137666,
  "_missing_rows": 12784,
  "_unique_missing_city_locality": 1689,
  "_preserved_numeric_overrides": 0,
  "_note": "Fill numeric INR/sqft values for null localities. Numeric values are reused in future runs.",
  "Alwar": {
    "60 Feet Road": null,
    "Ambedkar Nagar": null,
    "Basant Vihar": null,
    "Bhagwanpura": null,
    "Chikani": null,
    "Gandhi Nagar": null,
    "Goleta": null,
    "Indira Colony": null,
    "Itarana": null,
    "Jai Nagar": null,
    "Kabir Colony": null,
    "Kala Kuan": null,
    "Kesroli": null,
    "Kherado": null,
    "Lajpat Nagar": null,
    "MIA": null,
    "Malviya Nagar": null,
    "Mohalla Ladiya": null,
    "NEB Extn": null,
    "NEB Upaz Mandi": null,
    "Nagla Samawadi": null,
    "Naugaon": null,
    "Old Station Road": null,
    "Patel Nagar": null,
    "Ram Nagar": null,
    "Scheme -5": null,
    "Scheme -8": null,
    "Scheme-10": null,
    "Shahjahanpur": null,
    "Shiv Colony": null,
    "Shivaji Park": null,
    "Shivaji park": null,
    "Shri Ram Nagar": null,
    "Surya Nagar": null,
    "Tapukara": null,
    "Tehla": null,
    "Tijara": null,
    "Tijara Road": null,
    "Transport Nagar": null,
    "Tulera": null,
    "Vaishali Nagar": null,
    "Vijaynagar": null,
    "neemrana": null
  },
  "Bahadurgarh": {
    "Arya Nagar": null,
    "Dev Nagar": null,
    "Kherka Musalman": null,
    "Kherka Musalman, Sector 4A": null,
    "Nuna Majra": null,
    "Nuna Majra, Sector 36": null,
    "Old Industrial Area, Sector 36": null,
    "Ram Nagar": null,
    "Ranjeet Colony": null,
    "Sector 14": null,
    "Sector 3": null,
    "Sector 9": null,
    "Sector-02": null,
    "Sector-13": null,
    "Sector-6": null,
    "Sector-9A": null,
    "sector 28A": null,
    "sector 36": null,
    "sector 37": null
  },
  "Bhaini Khurd": {
    "Sector 45": null
  },
  "Faizupur Majra Neemka": {
    "Sector 76": null
  },
  "Faridabad": {
    "Air Force Road": null,
    "Ashoka Enclave 1, Sector 34": null,
    "Ashoka Enclave 1, Sector 35": null,
    "Ashoka Enclave 3, Sector 34": null,
    "Ashoka Enclave 3, Sector 42": null,
    "Ashoka Enclave Part 2": null,
    "Ashoka Enclave Part 3, Sector 34": null,
    "Ashoka Enclave Part 3, Sector 35": null,
    "Badarpur": null,
    "Baniawada": null,
    "Bhatia Colony": null,
    "Block B Dabua Colony": null,
    "Block E Sector 50": null,
    "Block G Piyush Heights": null,
    "Block S Sector 75": null,
    "Chajjan Nagar Village": null,
    "Charmwood Village, Sector 39": null,
    "Dayal Bagh Road": null,
    "Eros Garden, Sector 39": null,
    "Fajju Pur Village, Sector 76": null,
    "Fruit Garden": null,
    "Green Field Colony, Sector 41": null,
    "Green Field Colony, Sector 42": null,
    "Green Field Colony, Sector 43": null,
    "Greenfields": null,
    "Greenfields, Sector 43": null,
    "Huda Market Kartik Vihar": null,
    "Indra Complex Colony": null,
    "Indraprastha Colony, Sector 32": null,
    "Jajru": null,
    "Jawahar Colony Block D": null,
    "Jhar Sentli, Sector 57": null,
    "Kail Gaon, Sector 143": null,
    "Manjhawali": null,
    "Masjid Area": null,
    "Mathura Road": null,
    "Mathura Road, Sector 143": null,
    "Mewla Maharajpur, Sector 27": null,
    "Moti Colony": null,
    "Mujesar Village, Sector 24": null,
    "NIT 5": null,
    "Nangla Enclave Part 1": null,
    "Neemka Village, Sector 72-73": null,
    "Neharpar": null,
    "Neharpar, Sector 57": null,
    "Neharpar, Sector 72-73": null,
    "Nehru Ground": null,
    "New Baselwa Colony": null,
    "New Industrial Township": null,
    "New Industrial Township 1": null,
    "New Industrial Township 1 Block K": null,
    "New Industrial Township 2": null,
    "New Industrial Township 3": null,
    "New Industrial Township 3 Block F": null,
    "New Industrial Township 3 Block H": null,
    "New Industrial Township 5": null,
    "New Industrial Township 5 Block C": null,
    "New Industrial Township 5 Block M": null,
    "Old Faridabad, Sector 78": null,
    "Pali Village": null,
    "Palla Village": null,
    "Part 2 Parvatiya Colony": null,
    "Parvatiya Colony": null,
    "Rajiv Gandhi Colony": null,
    "Roshan Nagar": null,
    "Sahupura Ballabhgarh": null,
    "Sainik Colony": null,
    "Saral": null,
    "Saraswati Colony": null,
    "Sayad Wara": null,
    "Sector 143": null,
    "Sector 20": null,
    "Sector 20 Friends Colony": null,
    "Sector 21": null,
    "Sector 23A": null,
    "Sector 27A": null,
    "Sector 27C": null,
    "Sector 32": null,
    "Sector 34": null,
    "Sector 35": null,
    "Sector 36": null,
    "Sector 39": null,
    "Sector 42": null,
    "Sector 43": null,
    "Sector 50": null,
    "Sector 51": null,
    "Sector 52": null,
    "Sector 54": null,
    "Sector 57": null,
    "Sector 58": null,
    "Sector 6": null,
    "Sector 60": null,
    "Sector 75": null,
    "Sector 76": null,
    "Sector 77": null,
    "Sector 78": null,
    "Sherpur": null,
    "Shiv Durga Vihar": null,
    "Sohna Road": null,
    "Springfield Colony": null,
    "Subhash Colony": null,
    "Suraj Kund Badkhal Road": null,
    "Surajkund": null,
    "Surajkund, Sector 39": null,
    "Surajkund, Sector 41": null,
    "Surya Colony": null,
    "Surya Nagar Phase 2": null,
    "Surya Vihar": null,
    "Tirkha Colony": null
  },
  "Ghaziabad": {
    "Aditya Mega City": null,
    "Aditya Mega City, Sector 3": null,
    "Aditya Mega City, Sector 62": null,
    "Ahinsa Khand 1, Sector 62": null,
    "Ahinsa Khand 2, Sector 62": null,
    "Akash Nagar": null,
    "Amaatra Crystal": null,
    "Ambedkar Road": null,
    "Amrapali": null,
    "Amrit Nagar": null,
    "Anand Industrial Estate": null,
    "Anand Vihar": null,
    "Anand Vihar, Sector 14": null,
    "Anand Vihar, Sector 62": null,
    "Ankur Vihar": null,
    "Ansal East End": null,
    "Arthala": null,
    "Arya Nagar": null,
    "Asalat Nagar": null,
    "Asalatpur Farakh Nagar": null,
    "Ashiana Greens": null,
    "Ashok Vatika": null,
    "Avantika": null,
    "Bahrampur": null,
    "Balram Nagar": null,
    "Bamheta Village": null,
    "Bamheta Village, Sector 62/63": null,
    "Basantpur Saitli": null,
    "Bazaria": null,
    "Bel Colony": null,
    "Bhuapur": null,
    "Biharipura": null,
    "Bisrakh Road": null,
    "Block 10 Raj Nagar": null,
    "Block 21 Shipra Suncity": null,
    "Block 5 Sector 2": null,
    "Block A Rampuri": null,
    "Block B Nandgram": null,
    "Block B Sector 2 Vaishali": null,
    "Block B Shaheed Nagar": null,
    "Block B Shalimar Garden Extension 2": null,
    "Block C Indirapuram": null,
    "Block C Shaheed Nagar": null,
    "Block C Swaran Jayanti Puram": null,
    "Block D Lohia Nagar": null,
    "Block E Govindpuram": null,
    "Block E Nandgram": null,
    "Block I Govindpuram": null,
    "Brij Vihar": null,
    "Budh Vihar": null,
    "Bulandshahr Road Industrial Area": null,
    "Chipiyana Buzurg": null,
    "Chipiyana Buzurg Road": null,
    "Chipyana Khurd Urf Tigri": null,
    "Chiranjeev Vihar, Sector 4": null,
    "Christian Nagar, Sector 62": null,
    "D Block Nandgram": null,
    "D Block Pratap Vihar": null,
    "DLF Ankur Vihar": null,
    "DLF Dilshad Extention 2": null,
    "Dasna": null,
    "Dasna Dehat": null,
    "Dasna Gate": null,
    "Dayanand Nagar": null,
    "Delhi Gate": null,
    "Delhi Meerut Expressway": null,
    "Elaichipur": null,
    "Friends Coloney": null,
    "Friends Colony Asalat Nagar": null,
    "GB Nagar": null,
    "GDA Colony": null,
    "GDA Colony Shastri Nagar": null,
    "Gandhi Nagar": null,
    "Gangapuram": null,
    "Garhi": null,
    "Ghantaghar": null,
    "Ghaziabad Road": null,
    "Ghukna": null,
    "Girdharpur Sunarasi": null,
    "Gokul Dham Colony": null,
    "Grand Trunk Road": null,
    "Green Park": null,
    "Gulab Vatika": null,
    "Gulmohur Greens": null,
    "Gyan Khand 1, Sector 1": null,
    "Gyan Khand 2, Sector 19": null,
    "Gyan Khand 3, Sector 62": null,
    "Hapur Road": null,
    "Hindan Residential Area": null,
    "Hindon Air Force Station": null,
    "Indrapuri": null,
    "Indrapuri Colony": null,
    "Jaiprakash Nagar": null,
    "Jassipura": null,
    "Jawahar Nagar": null,
    "Judges Enclave": null,
    "Kaila Bhatta Village": null,
    "Kailash Nagar": null,
    "Kailash Puram": null,
    "Kala Patthar": null,
    "Kamma 1": null,
    "Kanawani Village": null,
    "Karera": null,
    "Karpuri Puram": null,
    "Kaushambi, Sector 12": null,
    "Kaushambi, Sector 14": null,
    "Kaushambi, Sector 62": null,
    "Kotgaon Village": null,
    "Krishna Garden Colony": null,
    "Krishna Kunj Kailash Puram": null,
    "Krishna Nagar": null,
    "Krishna Vihar Mandoli": null,
    "Lajpat Nagar": null,
    "Lajpat Nagar, Sector 4": null,
    "Lal Bagh Colony": null,
    "Lalbag Colony": null,
    "Laxmi Garden, Sector 11": null,
    "Loha Mandi Bulandshahr Road Industrial Area": null,
    "Lohia Nagar": null,
    "Loni Dehat": null,
    "Loni Industrial Area": null,
    "Loni Road": null,
    "Madhuban Bapudham": null,
    "Mahagunpuram": null,
    "Mahindra Enclave": null,
    "Makanpur": null,
    "Makanpur, Sector 62A": null,
    "Mandola": null,
    "Manoj Vihar": null,
    "Mansarovar Park Colony": null,
    "Mansi Vihar, Sector 23": null,
    "Marium Nagar": null,
    "Master Colony": null,
    "Masuri": null,
    "Matiyala": null,
    "Mayur Vihar Dasna": null,
    "Meerut Road": null,
    "Meerut Road Industrial Area": null,
    "Mehrauli": null,
    "Mishal Garhi": null,
    "Model Town": null,
    "Model Town West": null,
    "Modern Railway City": null,
    "Modern Railway City, Sector 1": null,
    "Modern Railway City, Sector 2": null,
    "Modern Railway City, Sector 8": null,
    "Modi Nagar": null,
    "Modinagar": null,
    "Mohan Nagar": null,
    "Morta": null,
    "Morta Village": null,
    "Morti": null,
    "Muhiddinpur Dabarsi": null,
    "Mukund Nagar": null,
    "Muradnagar": null,
    "NH 58": null,
    "NH 91": null,
    "Nai Basti Dundahera": null,
    "Nandgram": null,
    "Naveen Park": null,
    "Navyug Market": null,
    "Nayphal": null,
    "Nayphal, Sector 1": null,
    "Nayphal, Sector 8": null,
    "Neelmani Colony": null,
    "Neelpadam Kunj Complex": null,
    "Neelpadam Kunj Complex, Sector 4": null,
    "Neeti Khand 2": null,
    "Neeti Khand 2, Sector 62": null,
    "Neeti khand 3": null,
    "New Panchwati Colony": null,
    "Niti Khand 1, Sector 13": null,
    "Noor Nagar": null,
    "Nyay Khand 1, Sector 62": null,
    "Om Sai City": null,
    "Orange County": null,
    "Panchsheel Colony": null,
    "Panchsheel Enclave": null,
    "Panchvati Colony": null,
    "Pasonda": null,
    "Phase 1 Akash Nagar": null,
    "Pilkhuwa": null,
    "Pocket F Nehru Nagar 3": null,
    "Police Line": null,
    "Prem Nagar": null,
    "RK Puram": null,
    "Radha Kunj": null,
    "Rahul Garden": null,
    "Rahul Vihar": null,
    "Rahul Vihar 2nd": null,
    "Rahul Vihar, Sector 10": null,
    "Rail Vihar Manoj Vihar": null,
    "Raj Nagar Extension Nandgram": null,
    "Rajinder Nagar Industrial Area": null,
    "Rajnagar Sector 7": null,
    "Ram Park": null,
    "Rampark Extension": null,
    "Ramprastha Colony": null,
    "Ramprastha Colony, Sector 5": null,
    "Ramprastha Greens": null,
    "Ramprastha Greens, Sector 1": null,
    "Ramprastha Greens, Sector 9": null,
    "Razapur Road": null,
    "Sadiq Nagar": null,
    "Sadiqpur": null,
    "Sadullahabad Road": null,
    "Sahibabad Industrial Area": null,
    "Sahibabad Industrial Area Site 4": null,
    "Sahid Nagar": null,
    "Sanjay Colony": null,
    "Sanjay Nagar": null,
    "Sanjay Nagar, Sector 23": null,
    "Sarai Nazar Ali": null,
    "Sarvodaya Nagar": null,
    "Saubhagya Puram": null,
    "Sector 03": null,
    "Sector 13 Bulandshahr Road Industrial Area": null,
    "Sector 23": null,
    "Sector 3": null,
    "Sector C1 Trans Delhi Signature City": null,
    "Sewa Nagar": null,
    "Shahberi": null,
    "Shaheed Nagar": null,
    "Shahpur Bamheta": null,
    "Shahpur Bamheta, Sector 62A": null,
    "Shakti Khand 2, Sector 2": null,
    "Shakti Khand 3, Sector 1": null,
    "Shakti Khand 3, Sector 13": null,
    "Shakti Khand 4, Sector 11": null,
    "Shakti Khand 4, Sector 2": null,
    "Shakti Khand 4, Sector 62": null,
    "Shakti khand 1, Sector 10": null,
    "Shalimar Garden Extension 1": null,
    "Shalimar Garden Extension 1, Sector 2": null,
    "Shalimar Garden Extension 2": null,
    "Shalimar Garden Extension 2, Sector 3": null,
    "Shatabdipuram": null,
    "Shipra Suncity": null,
    "Shubh City": null,
    "Shyam Park Extension": null,
    "Shyam Park Main": null,
    "Siddharth Vihar": null,
    "Siddharth Vihar, Sector 62/63": null,
    "Siddhartha Vihar": null,
    "Siddhartha Vihar, Sector 03": null,
    "Siddhartha Vihar, Sector 10": null,
    "Siddhartha Vihar, Sector 11": null,
    "Siddhartha Vihar, Sector 132": null,
    "Siddhartha Vihar, Sector 3": null,
    "Siddhartha Vihar, Sector 62": null,
    "Siddhartha Vihar, Sector 7": null,
    "Siddhartha Vihar, Sector 8": null,
    "Sihani Chungi": null,
    "Sihani Gate": null,
    "Sikrod": null,
    "Sona Enclave": null,
    "Srajan Housing Society": null,
    "State Highway 57": null,
    "Swaran Jayanti Puram": null,
    "Taj Expressway": null,
    "Tila More": null,
    "Tronica City": null,
    "Tronica City Road": null,
    "Tronica City, Sector C3": null,
    "Turab Nagar": null,
    "Upper Ganga Canal Road": null,
    "Vaibhav Khand": null,
    "Vaishali Extension": null,
    "Vaishali Extension, Sector 5": null,
    "Vaishali Extension, Sector 6": null,
    "Vaishali Extension, Sector 9": null,
    "Vasundhara Indirapuram Road": null,
    "Vijay Nagar Colony": null,
    "Vikram Enclave": null,
    "Vivekanand Nagar": null,
    "Vivekanand Nagar Road": null,
    "khora": null
  },
  "Greater Noida": {
    "Advocate Society": null,
    "Alistonia Estate Pi 1 and 2": null,
    "Anand Ashray": null,
    "Bhagirath Vihar": null,
    "Bhanauta": null,
    "Block A Omicron 2": null,
    "Block B Omicron 2": null,
    "Block C Ansal Golf Links 1": null,
    "Block C Omicron 2": null,
    "Block C Sector MU 1": null,
    "Block D Omicron 2": null,
    "Block D Sector MU 1": null,
    "Bodaki": null,
    "Cassia Fistula Estate": null,
    "Cassia Sigma": null,
    "Chakrasia Estate": null,
    "Chorosia Estate": null,
    "Ebony Estate": null,
    "Ecotech II, Sector 3B": null,
    "GB Nagar": null,
    "Gulistanpur": null,
    "Gulmohar Estate Pi 1 and 2": null,
    "Jacaranda Estate": null,
    "Khodna Khurd": null,
    "Malakpur Village": null,
    "Maripat Road": null,
    "Phi 3 Block C, Sector P3": null,
    "Pocket 4 Phi 2": null,
    "RHO 2 Block A": null,
    "RHO 2 Block B": null,
    "Roza Yakubpur": null,
    "Sector Alpha Road": null,
    "Sigma 1 Block A": null,
    "Sigma 2 Block C": null,
    "Site C Road": null,
    "Stellar Sigma": null,
    "Taj Expressway": null,
    "Udyog Kendra 2": null
  },
  "Gurgaon": {
    "Alipur Sohna": null,
    "Alipur Sohna, Sector 61": null,
    "Ashok Vihar Phase 1": null,
    "Ashok Vihar Phase 2": null,
    "Ashok Vihar Phase 3 Extension": null,
    "Ashok Vihar Phase 3 Extension Block A": null,
    "Ashok Vihar Phase 3 Extension Block J": null,
    "Badsa": null,
    "Badshahpur Sohna Road": null,
    "Basai Road": null,
    "Basai Village, Sector 9B": null,
    "Begumpur Khatola, Sector 74A": null,
    "Bhora Kalan": null,
    "Bilaspur Pataudi Road": null,
    "Block 5 Phase 3 DLF": null,
    "Block C DLF Colony": null,
    "Block C Sushant Lok 3": null,
    "Block F DLF Phase 1": null,
    "Block F Suncity": null,
    "Block G DLF Phase 1": null,
    "Block H DLF Phase 1": null,
    "Block H South City 1": null,
    "Block J Mayfield Garden": null,
    "Block L South City 1": null,
    "Block M South City 1": null,
    "Block N Mayfield Garden": null,
    "Block S Phase 3 DLF": null,
    "Block T Phase 3 DLF": null,
    "Block U Phase 3 DLF": null,
    "Carterpuri Village, Sector 23A": null,
    "Central Park": null,
    "Chandan Vihar, Sector 110A": null,
    "Chauma Village": null,
    "Civil Lines": null,
    "Cyber City": null,
    "DLF City": null,
    "DLF City 4": null,
    "DLF City Phase 4": null,
    "DLF Garden Villas": null,
    "DLF Phase 1, Sector 26A": null,
    "DLF Phase 5, Sector 31": null,
    "DLF Phase 5, Sector 535": null,
    "DLF Phase 5, Sector 53G": null,
    "Davilal Nagar": null,
    "Delhi Gurgaon Expressway": null,
    "Dhankot Road": null,
    "Dharam Colony": null,
    "Dharam Colony Block E": null,
    "Dwarka Expressway": null,
    "Dwarka Expressway Link Road": null,
    "Dwarka Expressway, Sector 37D": null,
    "Faridabad Gurgaon Road": null,
    "Farrukh Nagar Panchgaon Road": null,
    "Farrukhnagarrular": null,
    "Farukh Nagar": null,
    "Garauli Kalan, Sector 37C": null,
    "Garauli Kalan, Sector 37D": null,
    "Garauli Khurd, Sector 37D": null,
    "Golf Course Extension Road": null,
    "Golf Course Extension Road, Sector 61": null,
    "Golf Course Road": null,
    "Gurugram Road": null,
    "Gurugram Road, Sector 37D": null,
    "Haileymandi": null,
    "Harchandpur Sohna": null,
    "Housing Boarding": null,
    "IMT Manesar": null,
    "IMT Manesar, Sector 8": null,
    "IMT Manesar, Sector M1": null,
    "IMT Manesar, Sector M9": null,
    "ITI Colony": null,
    "Jhanjraula": null,
    "Kadipur Industrial Area, Sector 37C": null,
    "Kaliawas Sultanpur Road": null,
    "Kapashera Samalkha Road": null,
    "Khaintawas": null,
    "Kherki Majra": null,
    "LIG Colony": null,
    "MG Road": null,
    "Mahrauli Gurgaon Road": null,
    "Manesar Road": null,
    "Maruti Kunj": null,
    "Medicity": null,
    "Mehrauli Gurgaon Road": null,
    "Model Town": null,
    "Model Town Sector 11": null,
    "Mohyal Colony": null,
    "NH 48": null,
    "Nathupur Village": null,
    "Naurangpur Tauru Road": null,
    "Nayagaon": null,
    "New Basti, Sector 8": null,
    "New Gurgaon": null,
    "New Palam Vihar Block G": null,
    "New Palam Vihar Block K1": null,
    "New Palam Vihar Phase 3": null,
    "New Palam Vihar Phase 3, Sector 110A": null,
    "New Railway Road": null,
    "Nirvana Country 2": null,
    "Nirvana Country, Sector 50A": null,
    "Nirvana Country, Sector 50G": null,
    "Nirvana Pocket 1": null,
    "Nirvana country Pocket H": null,
    "Nirvana country Pocket H, Sector 50G": null,
    "Noble Enclave": null,
    "Officers Colony": null,
    "Old Delhi Gurgaon Road": null,
    "Orchid Petals": null,
    "Palam Farms": null,
    "Palam Farms, Sector 23A": null,
    "Palam Vihar Extension": null,
    "Palam Vihar Extension, Sector 18S": null,
    "Palam Vihar Extension, Sector 23A": null,
    "Palam Vihar Pocket A": null,
    "Palam Vihar Pocket B": null,
    "Palam Vihar Pocket C": null,
    "Palam Vihar Pocket E": null,
    "Palam Vihar Pocket F": null,
    "Palam Vihar Pocket H": null,
    "Palwal Sohna Road": null,
    "Panchgaon": null,
    "Parsvnath Exotica": null,
    "Pataudi": null,
    "Patel Nagar": null,
    "Patel Nagar, Sector 15P": null,
    "Phase 1 New Palam Vihar": null,
    "Phase 2 Greenopolis": null,
    "Phase 2 Laxman Vihar": null,
    "Phase 2 New Palam Vihar": null,
    "Pocket J Palam Vihar": null,
    "Pocket K Palam Vihar": null,
    "Pratap Nagar": null,
    "Prem Nagar, Sector 11": null,
    "Rajendra Park Block B": null,
    "Rajendra Park Block C": null,
    "Rajendra Park Block D": null,
    "Rajendra Park Block G": null,
    "Ram Nagar, Sector 8": null,
    "Sadar Bazar": null,
    "Saini Colony": null,
    "Samaspur Village": null,
    "Sanjay Gram Colony": null,
    "Sector 10B": null,
    "Sector 11": null,
    "Sector 110A": null,
    "Sector 17A": null,
    "Sector 17B": null,
    "Sector 23A": null,
    "Sector 26A": null,
    "Sector 31": null,
    "Sector 37B": null,
    "Sector 37C": null,
    "Sector 37D": null,
    "Sector 52A": null,
    "Sector 61": null,
    "Sector 70A": null,
    "Sector 74A": null,
    "Sector 8": null,
    "Sector 81A": null,
    "Sector 82A": null,
    "Sector 9B": null,
    "Shanti Nagar, Sector 11": null,
    "Sheetla Colony": null,
    "Sheetla Colony, Sector 05": null,
    "Sheetla Mata Road": null,
    "Shiv Colony": null,
    "Shivaji Nagar, Sector 11": null,
    "Shyam Kunj": null,
    "Signature Signum 93": null,
    "Sohna Ballabgarh Road": null,
    "Sohna Road": null,
    "Sohna Road, Sector 6G": null,
    "Sohna Rural": null,
    "South City 1 Block C": null,
    "South City 1 Block D": null,
    "South City 1 Block E": null,
    "South City 1 Block G": null,
    "South City 1 Block K": null,
    "South City 1 Block O": null,
    "South City 1 Block P": null,
    "South City 1 Block Q": null,
    "South City 1 Block Q, Sector 404": null,
    "South City 2, Sector 491": null,
    "South City 2, Sector 49G": null,
    "South Gurgaon": null,
    "Southern Peripheral Road": null,
    "State Highway 17": null,
    "Surat Nagar Phase 1": null,
    "Sushant Lok 1 Block A": null,
    "Sushant Lok 1 Block B": null,
    "Sushant Lok 1 Block C": null,
    "Sushant Lok 1 Block D": null,
    "Sushant Lok 1 Block E": null,
    "Sushant Lok 3 Block A": null,
    "Sushant Lok 3 Block B": null,
    "Sushant Lok 3 Block F": null,
    "Sushant Lok 3 Extension": null,
    "Sushant Lok Phase 1": null,
    "Sushant Lok Phase 3": null,
    "Sushant Lok Phase 3, Sector 573": null,
    "Udyog Vihar Phase 1": null,
    "Ullahawas, Sector 61": null,
    "Vatika City": null,
    "Vatika Kunj Extension": null,
    "Vir Nagar, Sector 8": null
  },
  "Jhajjar": {
    "Beri": null,
    "Jhajjarrural": null,
    "Old Barafkhana Road": null,
    "yakubpur": null
  },
  "Karnal": {
    "Alpha International City": null,
    "Alpha International City, Sector 28A": null,
    "Alpha International City, Sector 29": null,
    "Anand Vihar": null,
    "Ansal Town": null,
    "Ashok Colony": null,
    "Ashoka Colony": null,
    "Budha Khera": null,
    "Budha Khera, Sector 32": null,
    "CHD City": null,
    "CHD City, Sector 45": null,
    "Chaman Garden": null,
    "Choudhary Colony": null,
    "Dayalpura Colony": null,
    "Dayanand Colony": null,
    "Grand Trunk Road, Sector 28": null,
    "Hansi Road Karnal": null,
    "Indri": null,
    "Janak Puri": null,
    "Jondla Village": null,
    "Kaithal Road": null,
    "Kanika Vihar": null,
    "Karam Singh Colony": null,
    "Karan Vihar, Sector 34": null,
    "Karnal City, Sector 35": null,
    "Kunjpura Road": null,
    "LIC Colony": null,
    "Mall Road": null,
    "Model Town": null,
    "NH - 1": null,
    "Narsi Village": null,
    "New Bahadur Chand Colony": null,
    "New Shivaji Complex": null,
    "Nilokheri": null,
    "Phusgarh Part": null,
    "Phusgarh Part, Sector 32": null,
    "Phusgarh Part, Sector 33": null,
    "Phusgarh Part, Sector 34": null,
    "Phusgarh Part, Sector 6": null,
    "Phusgarh Part, Sector 7": null,
    "R K Puram": null,
    "Railway Road": null,
    "Rajiv Puram": null,
    "Ram Nagar": null,
    "Ramesh Nagar": null,
    "Sadar Bazar": null,
    "Sector - 33": null,
    "Sector 1": null,
    "Sector 12": null,
    "Sector 13": null,
    "Sector 14": null,
    "Sector 16": null,
    "Sector 2": null,
    "Sector 29": null,
    "Sector 32": null,
    "Sector 33": null,
    "Sector 34": null,
    "Sector 35": null,
    "Sector 36": null,
    "Sector 4": null,
    "Sector 5": null,
    "Sector 6": null,
    "Sector 7": null,
    "Sector 8": null,
    "Sector 9": null,
    "Shakti Colony": null,
    "Shiv Colony": null,
    "Subhash Nagar": null,
    "Taraori": null,
    "Taraori, Sector 16": null,
    "Urban Estate": null,
    "Urban Estate, Sector 13": null,
    "Vasant Vihar": null
  },
  "Makarampur": {
    "Baldi, Sector 29": null
  },
  "Meerut": {
    "Ajanta Colony": null,
    "Ansal City": null,
    "Ansal Colony": null,
    "Ansal housing": null,
    "Ansal's Sushant City": null,
    "Ansals Sushant City": null,
    "Ansals Sushant City, Sector 3": null,
    "Ansals Sushant City, Sector 7": null,
    "Baghpat Road": null,
    "Bagpat": null,
    "Begam Bridge": null,
    "Begambagh": null,
    "Beripura": null,
    "Bhadora": null,
    "Bhagawatpura": null,
    "Bhola Road": null,
    "Bijli Bamba Bypass Road": null,
    "Brahmpuri": null,
    "Brij Kunj": null,
    "Budhana Gate": null,
    "Dashmesh nagar": null,
    "Daurala": null,
    "Daurli": null,
    "Defence Colony": null,
    "Defence Enclave": null,
    "Delhi Bye Pass": null,
    "Delhi Road": null,
    "Devlok": null,
    "Devpuri": null,
    "Dwarka puri": null,
    "Fazalpur": null,
    "Gagan Enclave": null,
    "Gagan Vihar": null,
    "Gandhi Nagar": null,
    "Ganga Dham": null,
    "Ganga Nagar": null,
    "Ganga Sagar": null,
    "Garh Road": null,
    "Ghanta ghar": null,
    "Gokul Vihar": null,
    "Green Wood City": null,
    "Gupta Colony": null,
    "Hapur Road": null,
    "Indra Puram": null,
    "Isha puram": null,
    "Islamabad": null,
    "Jagrati Vihar": null,
    "Jagrati Vihar, Sector 2": null,
    "Jagrati Vihar, Sector 8": null,
    "Jagriti Vihar": null,
    "Jagriti Vihar, Sector 2": null,
    "Jagriti Vihar, Sector 8": null,
    "Jai Bhim Nagar": null,
    "Jail chungi road": null,
    "Jainpur": null,
    "Jawahar Nagar": null,
    "Kalyannagar": null,
    "Kamla nagar": null,
    "Kankarkhera": null,
    "Kanker Khera": null,
    "Kanker Khera, Sector 1": null,
    "Khadoli": null,
    "Kila Parichit Garh": null,
    "Kirti palace": null,
    "Kishanpura": null,
    "Krishnanagar": null,
    "Lakhmi Vihar": null,
    "Lalkurti Bazar": null,
    "Lisari Road": null,
    "Lohia Nagar": null,
    "MDA, Sector 1": null,
    "MDA, Sector 4": null,
    "Madhav Puram": null,
    "Madhav Puram, Sector 4": null,
    "Madhavpuram": null,
    "Malyana": null,
    "Mangal pandey nagar": null,
    "Mawana": null,
    "Mawana Road": null,
    "Meenakshipuram": null,
    "Meerut Bye Pass": null,
    "Meerut Cantt": null,
    "Modi Puram": null,
    "Modipuram": null,
    "Mohanpuri": null,
    "Mohkam Pur": null,
    "Multan nagar": null,
    "NH-58": null,
    "Naibasti": null,
    "Nand Vihar": null,
    "Nangla Tashi": null,
    "Nangla Tashi Qasimpur": null,
    "Nauchandi": null,
    "Naval Vihar": null,
    "New Prabhat Nagar": null,
    "New Sainik Colony": null,
    "New multan nagar": null,
    "Noor Nagar": null,
    "Pallav puram": null,
    "Pallavpuram": null,
    "Panchsheel Colony": null,
    "Panchwati": null,
    "Pandav Nagar": null,
    "Partapur": null,
    "Pavli Khas": null,
    "Phase 1 Shradhapuri": null,
    "Phool Bagh Colony": null,
    "Police Lines": null,
    "Prabhat Nagar": null,
    "Prabhatnagar": null,
    "Prahlad Nagar": null,
    "Prempuri": null,
    "Radha Garden": null,
    "Rajbans Vihar": null,
    "Rajender puram": null,
    "Raksha puram": null,
    "Rakshapuram": null,
    "Rambagh Colony": null,
    "Ramgarhi": null,
    "Rampur Pawti": null,
    "Rishi Nagar": null,
    "Rithani": null,
    "Rohta Road": null,
    "Roorkee Road": null,
    "Sadar Bazar": null,
    "Sadr Bazar": null,
    "Sainik Vihar": null,
    "Saket": null,
    "Saraswati Lok": null,
    "Sardhana": null,
    "Sardhana Road": null,
    "Sector 5 Ansals Sushant City": null,
    "Sector 9 Shastri Nagar": null,
    "Shambhu nagar": null,
    "Sharda Puri": null,
    "Sharda Road": null,
    "Shastri Nagar": null,
    "Shastri Nagar, Sector 2": null,
    "Shastri Nagar, Sector 4": null,
    "Shastri Nagar, Sector 7": null,
    "Shastri Nagar, Sector 9": null,
    "Shatabdi nagar": null,
    "Shatabdi nagar, Sector 4": null,
    "Shatabdi nagar, Sector 5": null,
    "Shiv Puram": null,
    "Shiv shakti Vihar": null,
    "Shivshakti Nagar": null,
    "Shohrab Gate": null,
    "Shradhapuri Phase 1": null,
    "Shri Nangli Sahib": null,
    "Shyam Nagar": null,
    "Siwaya Jamalullapur": null,
    "Siwaya-Jamalullapur": null,
    "Sofipur": null,
    "Somdutt Vihar": null,
    "Sotiganj": null,
    "State bank colony": null,
    "Subhashnagar": null,
    "Suraj Kund": null,
    "Surya Nagar": null,
    "Surya Palace Colony": null,
    "Sushant city": null,
    "Takshila colony": null,
    "Tej Vihar": null,
    "Tejgarhi": null,
    "Tejgarhi, Sector 3": null,
    "Thapar Nagar": null,
    "Thaparnagar": null,
    "Transport Nagar": null,
    "Ved Vyas Puri -Phase 1": null,
    "Vedvyash puri": null,
    "Zonal park": null,
    "jainpur": null,
    "new Shambhu nagar": null,
    "sarrafa bazar": null,
    "shiv lok": null
  },
  "Muzaffarnagar": {
    "Adarsh Colony": null,
    "Almaspur": null,
    "Bachan Singh Colony": null,
    "Civil Lines North": null,
    "Civil Lines South": null,
    "Gandhi Colony": null,
    "Gandhi Nagar": null,
    "Jansath": null,
    "Kamal Nagar": null,
    "Khatauli": null,
    "Laddhawala": null,
    "Mahaveer Chowk": null,
    "Muzaffarnagar City": null,
    "New Mandi": null,
    "Niyazupura": null,
    "Rampuri": null,
    "Sakuntala Avas Vikash Colony": null,
    "Shamli": null,
    "Village Kookra": null
  },
  "New Delhi": {
    "A Block Saket, Sector 6": null,
    "Adarsh Enclave": null,
    "Adchini": null,
    "Africa Avenue": null,
    "Amar Colony Nangloi Extension": null,
    "Amrit Puri": null,
    "Amritapuri": null,
    "Ansari Nagar West": null,
    "Aram Park": null,
    "Arvind Nagar": null,
    "Asaf Ali Road": null,
    "Asalatpur Khadar": null,
    "Asola Homes": null,
    "Auchandi": null,
    "Avantika": null,
    "Avantika, Sector 1A": null,
    "Azad Market": null,
    "Azad Market Road": null,
    "Baba Faridpuri": null,
    "Baba Haridas Nagar Jharoda Kalan": null,
    "Babar Road": null,
    "Badusarai": null,
    "Bagdola": null,
    "Bahubali Extension": null,
    "Bakargarh": null,
    "Bakoli": null,
    "Baldev Park": null,
    "Balola": null,
    "Bandalo Wala Mohalla": null,
    "Bank Colony Durga Vihar": null,
    "Bankner": null,
    "Bapraula Extension": null,
    "Barakhamba": null,
    "Batla House": null,
    "Begum Pur, Sector 22": null,
    "Begumpur, Sector 22": null,
    "Behlolpur": null,
    "Benson Town": null,
    "Beri Wala Bagh": null,
    "Bhalswa Dairy": null,
    "Bhalswa Jahangir Village": null,
    "Bhama Shah Marg": null,
    "Bharat Nagar New Friends Colony": null,
    "Bhim Nagri": null,
    "Bhorgarh": null,
    "Block 11 East Patel Nagar": null,
    "Block 16 East Patel Nagar": null,
    "Block 32 East Patel Nagar": null,
    "Block A Karam Pura": null,
    "Block A Okhla": null,
    "Block A Pochanpur Colony": null,
    "Block A Sanjay Enclave": null,
    "Block B Dashrath Puri": null,
    "Block B Pochanpur Colony": null,
    "Block C Bhalswa": null,
    "Block C Dilshad Garden": null,
    "Block C Diplomatic Enclave": null,
    "Block C Nawada": null,
    "Block C New Multan Nagar": null,
    "Block D Block B Bharat Vihar, Sector 14": null,
    "Block E Bali Nagar": null,
    "Block E Shyam Vihar 1 Najafgarh": null,
    "Block F Karam Pura": null,
    "Block F Palam Extension, Sector 7": null,
    "Block F Sat Bari": null,
    "Block FD Shivaji Enclave": null,
    "Block GH 5 And 7": null,
    "Block I Karampura West": null,
    "Block I Khyala Village": null,
    "Block O Prasad Nagar": null,
    "Block R Dilshad Garden": null,
    "Block RZ Puran Nagar": null,
    "Block RZB Raja Puri Matiala": null,
    "Block VB Virender Nagar": null,
    "Block WZ Basai Dara Pur": null,
    "Block WZ Lajwanti Garden": null,
    "Block Y Diplomatic Enclave": null,
    "Brahampuri Road": null,
    "Brijwasi Colony": null,
    "CR Park Main Road": null,
    "Central Market Lajpat Nagar 2": null,
    "Chand Mohalla": null,
    "Chandan Vihar West Sant Nagar": null,
    "Chhajjupur": null,
    "Chilla Gaon": null,
    "Chirag Delhi": null,
    "Chirag Dilli": null,
    "Chirag Enclave": null,
    "Co operative Group Housing Societies Pitampura": null,
    "Commonwealth Games Village": null,
    "Cottage Enclave": null,
    "D Block Avantiva": null,
    "DDA Park Nihal Vihar": null,
    "DLF Farms": null,
    "Dabri Palam Road": null,
    "Dasghara": null,
    "Daya Basti": null,
    "Dayalpur": null,
    "Dayanand Colony Block C": null,
    "Deep Enclave": null,
    "Defence Area": null,
    "Delhi Cantonment": null,
    "Delhi Meerut Expressway, Sector 22A": null,
    "Delhi Race Club": null,
    "Delhi Road": null,
    "Dera": null,
    "Dhaka Village": null,
    "Dhaula Kuan": null,
    "Dhul Siras": null,
    "Dichaon Kalan": null,
    "Doctor APJ Abdul Kalam Road": null,
    "Double Storey": null,
    "Durga Puri": null,
    "East Janak Puri": null,
    "Engineers Enclave": null,
    "Faridabad Gurgaon Road": null,
    "Fatehpuri": null,
    "Front Block": null,
    "Fyaz Ganj": null,
    "GT Karnal Road": null,
    "Gafoor Nagar": null,
    "Gandhi Colony": null,
    "Ganga Ram Vatika": null,
    "Garhi Jharia Maria": null,
    "Gaushala Road": null,
    "Geetanjali Park": null,
    "Ghanta Ghar Road": null,
    "Gharoli": null,
    "Gohana": null,
    "Gokalpur East": null,
    "Gopal Nagar Fateh Nagar": null,
    "Gopal Vihar": null,
    "Goutampuri": null,
    "Goyla Village": null,
    "Green Avenue": null,
    "Green Valley Enclave": null,
    "Gulmohar Enclave Jamia Nagar": null,
    "Gurpreet Nagar Uttam Nagar": null,
    "Guru Angad Nagar West": null,
    "Guru Arjun Nagar": null,
    "Guru Nanak Nagar": null,
    "Guru Ramdas Nagar": null,
    "Gurunanak Pura Janakpuri": null,
    "HC Mathur Lane": null,
    "Haiderpur Road": null,
    "Haji Colony": null,
    "Hamdard Nagar": null,
    "Hardev Puri Gautam Nagar": null,
    "Hari Nagar Jaitpur": null,
    "Hari Park": null,
    "Hari Singh Park": null,
    "Hastsal Village": null,
    "Hauz Rani": null,
    "Himigiri Enclave": null,
    "Hyderabad House": null,
    "IGNOU Main Road": null,
    "ITI Jail Road": null,
    "Ibrahimpur": null,
    "Ibrahimpur Extn": null,
    "Indra Park Masudabad": null,
    "Indra Park Palam": null,
    "Indra Park Ram Datt Enclave": null,
    "Ishwar Nagar": null,
    "JJ Colony Sawda": null,
    "JNU Campus Old": null,
    "Jafrabad Main Road": null,
    "Jagatpuri Shahdara": null,
    "Jagdamba Vihar": null,
    "Janpath": null,
    "Janta Market Rajouri Garden": null,
    "Jantar Mantar Road": null,
    "Jawahar Park Laxmi Nagar": null,
    "Jeevan Niketan": null,
    "Jia Sarai": null,
    "Kailash Kunj": null,
    "Kakrola Road": null,
    "Kalan Mahal": null,
    "Kalindi Kunj Meethapur Road": null,
    "Kamla Nagar Market": null,
    "Kanjhawala Village": null,
    "Kapashera Samalkha Road": null,
    "Karampura West": null,
    "Karawal Nagar Main Road": null,
    "Kartar Nagar": null,
    "Kaushik Enclave Main Road": null,
    "Keshav Nagar": null,
    "Khadda Colony": null,
    "Khajoori Road": null,
    "Khan Market": null,
    "Khandsa Colony": null,
    "Khera Kalan": null,
    "Khureji Khas": null,
    "Khyber Pass": null,
    "Kilokri": null,
    "Kingsway Camp": null,
    "Kondli Extension": null,
    "Krishna Nagar Karol Bagh": null,
    "Krishna Nagar-Safdarjung Enclave": null,
    "Krishna Puri Krishna Park": null,
    "Lado Sarai Extension": null,
    "Lady Hardinge Medical College": null,
    "Lakshmi Park": null,
    "Lal Quarter": null,
    "Ludlow Castle": null,
    "MS Park": null,
    "Madanpur Khadar Extension": null,
    "Madanpur Khadar Village": null,
    "Madhu Vihar Patparganj": null,
    "Mahavir Campus": null,
    "Main Market Shakarpur": null,
    "Main Mother Dairy Road": null,
    "Main Rajapuri Road": null,
    "Major Bhupinder Singh Nagar": null,
    "Malcha": null,
    "Mall Road": null,
    "Mangalpuri 2": null,
    "Masihgarh": null,
    "Matiala Road": null,
    "Maurice Nagar": null,
    "Mayur Vihar Phase 3 Main Road": null,
    "Meer Vihar": null,
    "Mehram Nagar": null,
    "Mehrauli Badarpur Road": null,
    "Mehrauli Gurgaon Road": null,
    "Milakpur Kohi Rangpuri": null,
    "Mirpur Turk": null,
    "Mohammadpur Majri": null,
    "Mohan Park Laxmi Nagar": null,
    "Molarband School Road": null,
    "Mori Gate": null,
    "Moti Bagh South": null,
    "Mukherji Nagar Road": null,
    "Mukhram Garden": null,
    "NCERT Campus": null,
    "Nai Walan": null,
    "Najafgarh Road": null,
    "Najafgarh Thana Road": null,
    "Nanak Heri Village": null,
    "Nanak Heri Village, Sector 37D": null,
    "Nand Nagri": null,
    "Nanda Block": null,
    "Narela Mandi": null,
    "National Park": null,
    "Nauroji Nagar": null,
    "Nazafgarh Gurgaon Road": null,
    "Nehru Market": null,
    "Netaji Nagar": null,
    "Netaji Subhash Place": null,
    "New Colony Khirki Extension": null,
    "New Layal Pur": null,
    "New Modern Shahdara": null,
    "Nilothi Village": null,
    "Nimri Colony Phase 4": null,
    "Niranjan Park": null,
    "Noida Link Road": null,
    "Noor Nagar": null,
    "Okhla Estate Marg": null,
    "Okhla Industrial Area": null,
    "Okhla Road": null,
    "Old Delhi": null,
    "Old Janki Puri": null,
    "Old Palam Road": null,
    "Old Seemapuri": null,
    "Old Shahabad Muhammad Pur": null,
    "Pahar Ganj": null,
    "Palam Marg": null,
    "Palika Bazar": null,
    "Palla": null,
    "Panchkuian Marg": null,
    "Panchsheel Extension": null,
    "Panchsheel Marg": null,
    "Pandav Nagar Shadipur": null,
    "Paprawat": null,
    "Patpar Ganj Road": null,
    "Pitampura Road": null,
    "Pocket 13 Mangalpuri I": null,
    "Pocket A New Krishna Park": null,
    "Pocket C New Krishna Park": null,
    "Possangipur": null,
    "Pratap Enclave": null,
    "Pratap Nagar Mandoli": null,
    "Prem Nagar Janakpuri": null,
    "President's Estate, Sector 23B": null,
    "Press Colony": null,
    "Punchsheel Marg": null,
    "Punjabi Basti": null,
    "Punjabi Basti Subzi Mandi": null,
    "Pusa": null,
    "Pushkar Enclave": null,
    "Pushp Vihar": null,
    "Pushp Vihar, Sector 5": null,
    "Qutab Institutional Area": null,
    "R.K. Puram": null,
    "RK Puram": null,
    "Radheypuri": null,
    "Raghubarpura": null,
    "Raja Puri": null,
    "Raja Puri Madhu Vihar": null,
    "Raja Puri, Sector 3": null,
    "Rajendra Park Nangloi Extension": null,
    "Rajendra Park Rajinder Nagar": null,
    "Rajgarh Colony": null,
    "Rajpur Road Police Lines": null,
    "Ramprastha Greens": null,
    "Rana Ji Enclave": null,
    "Ranhola Extesion": null,
    "Resettlement Colony": null,
    "Ring Road": null,
    "Rohini Institutional Area": null,
    "Rohini Institutional Area, Sector 5": null,
    "Roshanpura": null,
    "Sadar Bazar Road": null,
    "Safipur": null,
    "Saiyad Ul Ajaib Extn": null,
    "Samaypur": null,
    "Samaypur Badli Metro Road": null,
    "Sangam Vihar Dharampura": null,
    "Sanjay Nagar Gulabi Bagh": null,
    "Sant Nagar East of Kailash": null,
    "Sant Nagar Marg": null,
    "Sarai Jullena": null,
    "Sarai Pipal Thala": null,
    "Satbari": null,
    "Satyawati Colony": null,
    "Second Avenue": null,
    "Sector 11": null,
    "Sector 3": null,
    "Shahabad Muhammadpur Village": null,
    "Shahabad Muhammadpur Village, Sector 8": null,
    "Shahbad Daulatpur Village": null,
    "Shalimar Bagh Poorvi": null,
    "Shalimar Village": null,
    "Sheikh Sarai Village": null,
    "Shiv Block": null,
    "Shiv Park Kakrola": null,
    "Shiv Vihar Sihvram Park": null,
    "Shiv Vihar West": null,
    "Shiva Enclave Hastsal": null,
    "Shree Nagar": null,
    "Shri Ram Colony": null,
    "Sidora Kalan": null,
    "Siri Fort": null,
    "Siri Fort Road": null,
    "Soami Nagar South": null,
    "Sri Niwaspuri": null,
    "Sriniwaspuri Extension": null,
    "Subhash Mohalla": null,
    "Subhash Park Extension 2": null,
    "Sulahkul Vihar": null,
    "Sultanpur Mandi Road": null,
    "Sultanpur Road": null,
    "Supreme Enclave": null,
    "Swami Dayanand Enclave": null,
    "Taimoor Nagar": null,
    "Tanki Road": null,
    "Teliwara": null,
    "Tilak Marg": null,
    "Tilangpur Kotla": null,
    "Todarmal Road": null,
    "Todermal Road Area": null,
    "Tolstoy Road": null,
    "Trilok Puri Road": null,
    "Turkman Gate": null,
    "Undri": null,
    "Upadhyay Block": null,
    "Uthandi": null,
    "Uttam Nagar Block C, Sector 11": null,
    "Uttam Vihar": null,
    "Vasant Kunj Institutional Area": null,
    "Vijay Vihar Uttam Nagar": null,
    "Vikas Nagar Hastsal": null,
    "Vikas Puri Extension Part 1": null,
    "Vikaspuri Pocket DG2": null,
    "Vinod Nagar East": null,
    "Vishwakarma Park": null,
    "Vishwas Park Extension": null,
    "Vivekanand Puri": null,
    "Ward No 8": null,
    "Ward Number 1": null,
    "West Cabin Block": null,
    "West End": null,
    "West End Greens": null,
    "Western Avenue": null,
    "Zamrudpur": null
  },
  "Noida": {
    "Bahlolpur": null,
    "Bhangel": null,
    "Bhangel, Sector 505": null,
    "Chaukhandi": null,
    "Chipiyana Buzurg": null,
    "Chotpur Colony": null,
    "Dadri Main Road": null,
    "Delhi Meerut Expressway": null,
    "Film City": null,
    "Film City, Sector 16C": null,
    "Film City, Sector 22D": null,
    "Garhi": null,
    "Gejha Road": null,
    "Goutam Buddh Nagar": null,
    "Goutam Buddh Nagar, Sector 01": null,
    "Hosiery Complex": null,
    "Indira Vihar, Sector 62A": null,
    "Jalvayu Vihar, Sector 25O": null,
    "Jaypee Wishtown Internal Road": null,
    "Kendriya Vihar 2": null,
    "Khora Colony, Sector 62A": null,
    "Kompally": null,
    "Kondli": null,
    "Kondli Gharoli": null,
    "Noida Golf Course, Sector 151A": null,
    "Noida Greater Noida Expressway": null,
    "Noida Phase 2": null,
    "Omicron 1": null,
    "Pari Chowk": null,
    "Phase 2": null,
    "Pimpri Chinchwad": null,
    "Prahlad Colony": null,
    "Prateek Wisteria": null,
    "Rajat Vihar": null,
    "Rajeev Nagar": null,
    "Salarpur": null,
    "Salarpur, Sector 505": null,
    "Sarfabad": null,
    "Sarfabad, Sector 505": null,
    "Sector 143A": null,
    "Sector 33A": null,
    "Sector 62A": null,
    "Sector 94A": null,
    "Shaheed Arjun Sardana Marg": null,
    "Shaheed Captain Manoj Pandey Marg": null,
    "Shiv Park, Sector 62A": null,
    "Sinhgad Road": null,
    "Sorkha": null,
    "Surajpur": null,
    "Taj Expressway": null,
    "Udhyog Marg, Sector 16C": null,
    "Vivek Vihar": null
  },
  "Palwal": {
    "Adarsh Colony": null,
    "Alapur": null,
    "Bamni Khera": null,
    "Hathin": null,
    "Hodal": null,
    "Krishna Colony": null,
    "Krishna colony": null,
    "Link Road": null,
    "Mathura Road": null,
    "Mohan Nagar": null,
    "NH-2": null,
    "NH-2, Sector 5": null,
    "New Colony": null,
    "New Colony Extension": null,
    "Omaxe City": null,
    "Palwal Region": null,
    "Palwalrural": null,
    "Palwalrural, Sector 2": null,
    "Panchwati Colony": null,
    "Prakash Vihar Colony": null,
    "Ram Nagar": null,
    "Sector 2 Huda": null,
    "Sector 5": null,
    "Sector-6": null,
    "Shiv Colony": null,
    "Shiv Vihar": null
  },
  "Panipat": {
    "Ansal API": null,
    "Baberpur Mandi": null,
    "Baberpur Mandi, Sector 40": null,
    "Batra Colony": null,
    "Desraj Colony": null,
    "Grand Trunk Road": null,
    "HUDA": null,
    "HUDA, Sector 18": null,
    "HUDA, Sector 6": null,
    "Hari Bagh Colony": null,
    "Hari Nagar": null,
    "Housing Board Colony": null,
    "Huda, Sector 11": null,
    "Huda, Sector 12": null,
    "Huda, Sector 25": null,
    "Jattal Road": null,
    "Kabri": null,
    "Krishanpura": null,
    "Model Town": null,
    "NATIONAL HIGHWAY, Sector 40": null,
    "NH 1": null,
    "NH 1, Sector 37": null,
    "Netaji Colony": null,
    "New Ramesh Nagar": null,
    "Nizampur": null,
    "Noorwala Village": null,
    "Salarganj Gate": null,
    "Samalkha": null,
    "Sanjay chowk": null,
    "Sat Kartar Nagar": null,
    "Sector 11": null,
    "Sector 11 Huda": null,
    "Sector 12 Huda": null,
    "Sector 13 To 17": null,
    "Sector 18 Huda": null,
    "Sector 24": null,
    "Sector 25 Huda": null,
    "Sector 36": null,
    "Sector 4 Eldeco Estate": null,
    "Sector 40": null,
    "Sector 6 Huda": null,
    "Sector-19": null,
    "Sector-25 Industrial Part 2": null,
    "Sector-40": null,
    "Sector-40 Huda": null,
    "Sector-8": null,
    "Shanti Nagar": null,
    "Sonali Road": null,
    "Sondhapur": null,
    "Sushant City": null,
    "TDI City": null,
    "Tehsil Camp": null,
    "Vijay Nagar": null,
    "Vikash Nagar": null,
    "Virat Nagar": null,
    "Virat Nagar, Sector 1": null,
    "Yamuna Enclave": null
  },
  "Panipat Taraf Ansar": {
    "HUDA": null,
    "HUDA, Sector 25": null,
    "Tehsil Camp": null
  },
  "Rewari": {
    "Ajay Nagar": null,
    "Anaj Mandi": null,
    "Bhakti Nagar": null,
    "Dev Nagar": null,
    "Dhaliawas": null,
    "Dhaliawas, Sector 26": null,
    "Dharuhera": null,
    "G.T.Road Rewari": null,
    "Garhi Bolni Road": null,
    "Ghisa Ki Dhani": null,
    "Jatusana": null,
    "Kayasthwara Mohalla": null,
    "Kayasthwara Mohalla, Sector 5": null,
    "Krishna Nagar": null,
    "Krishna Nagar, Sector 4": null,
    "Model Town": null,
    "N H 8": null,
    "NH 71B": null,
    "Railway Colony": null,
    "Rampura Railway Crossing": null,
    "Sector 1": null,
    "Sector 3": null,
    "Sector 4": null,
    "Shahbajpur Khalsa": null,
    "Shakti Nagar": null,
    "Shanti Nagar": null,
    "Shanti Nagar, Sector 5": null,
    "Shanti nagar": null,
    "Uttam Nagar": null,
    "Vijay Nagar": null,
    "bawal": null,
    "ramsinghpura": null,
    "uttam nagar": null,
    "yadav nagar": null
  },
  "Rohtak": {
    "Arya Nagar": null,
    "Azad Garh": null,
    "Babra Mohalla": null,
    "Bhiwani Rohtak Road": null,
    "Company Bagh": null,
    "DLF Colony": null,
    "Dariyao Nagar": null,
    "Delhi Road, Sector 27A": null,
    "Delhi Rohtak Road": null,
    "Dev Colony": null,
    "Durga Colony": null,
    "Ekta Colony": null,
    "Gandhi Nagar": null,
    "Geeta Colony": null,
    "Gohana Adfda": null,
    "Guru Nanak Pura": null,
    "Hari Singh Colony": null,
    "Jagdish Colony": null,
    "Janta Colony": null,
    "Jhajjar Road": null,
    "Jhajjar Road, Sector 22D": null,
    "Kanheli": null,
    "Kewal Ganj": null,
    "Kirpal Nagar": null,
    "Laxmi Nagar": null,
    "Mahabir Colony": null,
    "Maina": null,
    "Meham Chouksi": null,
    "Min Housing Board Colony": null,
    "Model Town": null,
    "Nehru Colony": null,
    "New Anaj Mandi": null,
    "New Bus Stand": null,
    "New Grain Market": null,
    "New Janta Colony": null,
    "Old Bus Stand Rohtak": null,
    "Omaxe Society": null,
    "Partap Nagar": null,
    "Preet Vihar": null,
    "Prem Nagar": null,
    "Rajeev Nagar": null,
    "Rajender Nagar": null,
    "Rajender Nagar, Sector 6": null,
    "Rajendra Colony": null,
    "Rajendra Nagar, Sector 6": null,
    "Ram Gopal Colony": null,
    "Ram Gopal Colony, Sector 1": null,
    "Ram Nagar": null,
    "Rishi Nagar": null,
    "Rohtak Station Diary Mohalla": null,
    "Sampla": null,
    "Sector 1": null,
    "Sector 14": null,
    "Sector 2": null,
    "Sector 28": null,
    "Sector 3": null,
    "Sector 3 (P)": null,
    "Sector 30 Commercial": null,
    "Sector 35 Suncity Township I": null,
    "Sector 36 Suncity Township I": null,
    "Sector 36A": null,
    "Sector 37": null,
    "Sector 3P": null,
    "Sector 4": null,
    "Sector-1": null,
    "Sector-2": null,
    "Sector-26": null,
    "Sector-28": null,
    "Sector-36A": null,
    "Sector-4": null,
    "Sector-5": null,
    "Shastri Nagar": null,
    "Shivaji Colony": null,
    "Shori Market": null,
    "Shyam Colony": null,
    "Sonipat Road": null,
    "Srinagar Colony": null,
    "Subhash Nagar": null,
    "Sukhpura Chowk": null,
    "Suncity": null,
    "Suncity Township-I, Sector 34": null,
    "Suncity Township-I, Sector 35": null,
    "Suncity Township-I, Sector 36": null,
    "Suncity, Sector 34": null,
    "Surya Nagar": null,
    "Tilak Nagar": null,
    "Vijay Nagar": null,
    "Vikas Nagar": null,
    "Vinay Nagar": null,
    "Vishal Nagar": null
  },
  "Sonipat": {
    "Ansal API": null,
    "Ansal API, Sector 62": null,
    "Badh Khalsa, Sector 61": null,
    "Balmiki Basti": null,
    "Barhi": null,
    "Bayanpur": null,
    "Dev Nagar": null,
    "Ganaur": null,
    "Gannaur": null,
    "Gohana": null,
    "Gohana Road": null,
    "Grand Trunk Road": null,
    "Grand Trunk Road, Sector 8": null,
    "Indira Colony": null,
    "Jeevan Vihar": null,
    "KMP Expy": null,
    "Kharkhoda": null,
    "Kundli": null,
    "Kundli, Sector 10": null,
    "Kundli, Sector 33": null,
    "Kundli, Sector 35": null,
    "Kundli, Sector 61": null,
    "Kundli, Sector 64": null,
    "Malviya Nagar": null,
    "Mehlana Road": null,
    "Model Town": null,
    "Mohalla Kalan": null,
    "Murthal": null,
    "NH-1": null,
    "NH-1, Sector 19": null,
    "Nangal Khurd, Sector 19": null,
    "Nangal Khurd, Sector 8": null,
    "Narender Nagar": null,
    "New Mahavir Colony": null,
    "Old DC Road": null,
    "Omaxe City": null,
    "Pargati Nagar": null,
    "Parsvanath City": null,
    "Patla, Sector 63": null,
    "Rai": null,
    "Rai, Sector 35": null,
    "Rasoi": null,
    "Rath dhana sonipat road": null,
    "Sector 10": null,
    "Sector 12": null,
    "Sector 13": null,
    "Sector 14": null,
    "Sector 15": null,
    "Sector 16": null,
    "Sector 18": null,
    "Sector 19": null,
    "Sector 23": null,
    "Sector 26": null,
    "Sector 27": null,
    "Sector 3": null,
    "Sector 30": null,
    "Sector 33": null,
    "Sector 34": null,
    "Sector 35": null,
    "Sector 58": null,
    "Sector 61": null,
    "Sector 64": null,
    "Sector 7": null,
    "Sector 8": null,
    "Sector 9": null,
    "Shastri Colony": null,
    "Sikka Colony": null,
    "Sonipat City, Sector 34": null,
    "Sonipat Road": null,
    "TDI City Kundli": null,
    "TDI City Kundli, Sector 59": null,
    "TDI City Kundli, Sector 61": null,
    "TDI City Kundli, Sector 64": null,
    "TDI Green City": null,
    "Vijay Nagar": null,
    "West Ram Nagar": null,
    "patel nagar": null
  }
}